{
    "configurations": [
        {
            "name": "Pico",
            "compilerPath": "/usr/bin/clang",
            "cStandard": "c11",
            "cppStandard": "c++17",
            "intelliSenseMode": "macos-clang-x64",
            "includePath": [
                "${workspaceFolder}/**",
                "${workspaceFolder}/src/pico/**",
                "${workspaceFolder}/build/pico",
                "/Users/dave/GitHub/pico/pico-sdk/**"
            ],
            "compileCommands": "${workspaceFolder}/build/pico/compile_commands.json"
        }
    ],
    "version": 4
}
